LICENSE
MANIFEST.in
README.md
setup.cfg
setup.py
src/huaytools/__init__.py
src/huaytools.egg-info/PKG-INFO
src/huaytools.egg-info/SOURCES.txt
src/huaytools.egg-info/dependency_links.txt
src/huaytools.egg-info/requires.txt
src/huaytools.egg-info/top_level.txt
src/huaytools/extensions/__init__.py
src/huaytools/extensions/abc_ex.py
src/huaytools/extensions/dict_ex.py
src/huaytools/utils/__init__.py
src/huaytools/utils/_common.py
src/huaytools/utils/dataclass_utils.py
src/huaytools/utils/markdown_utils.py
src/huaytools/utils/python_utils.py
tests/__init__.py
tests/extensions/__init__.py
tests/extensions/test_abc_ex.py
tests/extensions/test_dict_ex.py
tests/utils/__init__.py
tests/utils/test__common.py
tests/utils/test_dataclass_utils.py
tests/utils/test_markdown_utils.py
tests/utils/test_python_utils.py