Metadata-Version: 2.1
Name: huaytools
Version: 1.0.4
Summary: HuaYang's personal tool library.
Home-page: https://github.com/imhuay/huaytools
Author: HuaYang
Author-email: imhuay@163.com
License: MIT
Classifier: Programming Language :: Python :: 3.7
Classifier: Programming Language :: Python :: 3.8
Classifier: Programming Language :: Python :: 3.9
Classifier: Programming Language :: Python :: 3.10
Classifier: Intended Audience :: Developers
Classifier: License :: OSI Approved :: MIT License
Classifier: Operating System :: MacOS
Classifier: Operating System :: POSIX :: Linux
Classifier: Operating System :: Microsoft :: Windows
License-File: LICENSE
